tfyolo/__init__.py
tfyolo/configs/__init__.py
tfyolo/configs/config.py
tfyolo/configs/yolo-l-mish.yaml
tfyolo/configs/yolo-m-mish.yaml
tfyolo/configs/yolo-s-mish.yaml
tfyolo/configs/yolo-x-mish.yaml
tfyolo/data.py
tfyolo/dataset/__init__.py
tfyolo/dataset/augment_data.py
tfyolo/dataset/create_anchor.py
tfyolo/dataset/image_utils.py
tfyolo/dataset/label_anchor.py
tfyolo/dataset/load_data.py
tfyolo/dataset/prepare_data.py
tfyolo/dataset/read_data.py
tfyolo/layers/__init__.py
tfyolo/layers/module.py
tfyolo/model.py
tfyolo/models/__init__.py
tfyolo/models/loss.py
tfyolo/models/metrics.py
tfyolo/models/optimizer.py
tfyolo/models/post_process.py
tfyolo/models/yolo3.py
tfyolo/models/yolo5.py
tfyolo-0.0.1.dist-info/LICENSE
tfyolo-0.0.1.dist-info/WHEEL
tfyolo-0.0.1.dist-info/METADATA
tfyolo-0.0.1.dist-info/RECORD
