Metadata-Version: 2.1
Name: tfyolo
Version: 0.0.1
Summary: Series yolo detection in TensorFlow
Home-page: https://tfyolo.readthedocs.io
Author: Longxing Tan
Requires-Python: >=3.8,<3.11
Classifier: Intended Audience :: Developers
Classifier: Intended Audience :: Science/Research
Classifier: License :: OSI Approved :: MIT License
Classifier: Programming Language :: Python :: 3
Classifier: Programming Language :: Python :: 3.8
Classifier: Programming Language :: Python :: 3.9
Classifier: Programming Language :: Python :: 3.10
Classifier: Programming Language :: Python :: 3
Classifier: Programming Language :: Python :: 3.6
Classifier: Programming Language :: Python :: 3.7
Classifier: Programming Language :: Python :: 3.8
Classifier: Topic :: Scientific/Engineering
Classifier: Topic :: Scientific/Engineering :: Artificial Intelligence
Classifier: Topic :: Scientific/Engineering :: Mathematics
Classifier: Topic :: Software Development
Classifier: Topic :: Software Development :: Libraries
Classifier: Topic :: Software Development :: Libraries :: Python Modules
Requires-Dist: matplotlib
Requires-Dist: optuna (>=2.3.0,<3.0.0)
Requires-Dist: pandas (>=1.3.0,<2.0.0)
Requires-Dist: scikit-learn (>=0.24,<1.2)
Requires-Dist: scipy (>=1.8,<2.0)
Requires-Dist: tensorflow (>=2.4.1,<3.0.0)
Project-URL: Documentation, https://tfyolo.readthedocs.io
Project-URL: Repository, https://github.com/LongxingTan/tf-yolo
